install.py
install_is_pip_install-1.0.dist-info/LICENSE
install_is_pip_install-1.0.dist-info/METADATA
install_is_pip_install-1.0.dist-info/WHEEL
install_is_pip_install-1.0.dist-info/top_level.txt
install_is_pip_install-1.0.dist-info/RECORD
