Metadata-Version: 2.1
Name: install-is-pip-install
Version: 1.0
Summary: Alias 'install' to 'pip install'
Author-email: David Buchanan <d@vidbuchanan.co.uk>
Project-URL: Homepage, https://github.com/DavidBuchanan314/install-is-pip-install
Project-URL: Issues, https://github.com/DavidBuchanan314/install-is-pip-install/issues
Classifier: Programming Language :: Python :: 3
Classifier: License :: OSI Approved :: MIT License
Classifier: Operating System :: OS Independent
Requires-Python: >=3
License-File: LICENSE
